example_pkg_cloos/__init__.py
example_pkg_cloos/cli.py
example_pkg_cloos/utils.py
example_pkg_cloos-3.0.1.dist-info/LICENSE
example_pkg_cloos-3.0.1.dist-info/METADATA
example_pkg_cloos-3.0.1.dist-info/WHEEL
example_pkg_cloos-3.0.1.dist-info/entry_points.txt
example_pkg_cloos-3.0.1.dist-info/top_level.txt
example_pkg_cloos-3.0.1.dist-info/RECORD
