Metadata-Version: 2.1
Name: example-pkg-cloos
Version: 3.0.1
Summary: A example package to learn and test Python packaging.
Author-email: Christian Loos <cloos@netsandbox.de>
License: MIT License
Project-URL: Documentation, https://github.com/netsandbox/python_example_pkg_cloos
Project-URL: Homepage, https://github.com/netsandbox/python_example_pkg_cloos
Project-URL: Issues, https://github.com/netsandbox/python_example_pkg_cloos/issues
Project-URL: Source, https://github.com/netsandbox/python_example_pkg_cloos
Classifier: Development Status :: 5 - Production/Stable
Classifier: Environment :: Console
Classifier: Intended Audience :: Developers
Classifier: License :: OSI Approved :: MIT License
Classifier: Natural Language :: English
Classifier: Operating System :: POSIX
Classifier: Operating System :: POSIX :: Linux
Classifier: Programming Language :: Python
Classifier: Programming Language :: Python :: 3
Classifier: Programming Language :: Python :: 3 :: Only
Classifier: Programming Language :: Python :: 3.7
Classifier: Programming Language :: Python :: 3.8
Classifier: Programming Language :: Python :: 3.9
Classifier: Programming Language :: Python :: 3.10
Classifier: Topic :: Software Development
Classifier: Topic :: Software Development :: Build Tools
Classifier: Topic :: Software Development :: Libraries
Classifier: Topic :: Software Development :: Libraries :: Python Modules
Classifier: Topic :: Software Development :: Testing
Requires-Python: >=3.7
License-File: LICENSE
Requires-Dist: click (>=4.0)
